AUTHORS
LICENSE
MANIFEST.in
README.rst
setup.py
src/facio/__init__.py
src/facio/base.py
src/facio/config.py
src/facio/exceptions.py
src/facio/run.py
src/facio/state.py
src/facio/template.py
src/facio/vcs.py
src/facio.egg-info/PKG-INFO
src/facio.egg-info/SOURCES.txt
src/facio.egg-info/dependency_links.txt
src/facio.egg-info/not-zip-safe
src/facio.egg-info/requires.txt
src/facio.egg-info/top_level.txt
src/facio/bin/facio
src/facio/default/index.html
src/facio/default/css/bootstrap.css
src/facio/hooks/__init__.py
src/facio/hooks/django/__init__.py
src/facio/hooks/django/secret.py
src/facio/hooks/python/__init__.py
src/facio/hooks/python/setup.py
src/facio/hooks/python/virtualenv.py