Metadata-Version: 1.1
Name: facio
Version: 2.0.0
Summary: Project scaffolding using custom templates.
Home-page: http://facio.readthedocs.org
Author: Christopher John Reeves
Author-email: hello@chris.reeves.io
License: BSD
Platform: UNKNOWN
Classifier: Environment :: Console
Classifier: Development Status :: 5 - Production/Stable
Classifier: Programming Language :: Python
Classifier: Programming Language :: Python :: 2.6
Classifier: Programming Language :: Python :: 2.7
Classifier: Programming Language :: Python :: 3.2
Classifier: Programming Language :: Python :: 3.3
Classifier: Intended Audience :: Developers
Classifier: Operating System :: Unix
Classifier: License :: OSI Approved :: BSD License
Classifier: Topic :: Software Development
Classifier: Topic :: Software Development :: Libraries :: Python Modules
